nonebot/adapters/spigot/__init__.py
nonebot/adapters/spigot/adapter.py
nonebot/adapters/spigot/bot.py
nonebot/adapters/spigot/collator.py
nonebot/adapters/spigot/config.py
nonebot/adapters/spigot/event.py
nonebot/adapters/spigot/message.py
nonebot/adapters/spigot/utils.py
nonebot_adapter_spigot-0.0.5.dist-info/LICENSE
nonebot_adapter_spigot-0.0.5.dist-info/METADATA
nonebot_adapter_spigot-0.0.5.dist-info/WHEEL
nonebot_adapter_spigot-0.0.5.dist-info/top_level.txt
nonebot_adapter_spigot-0.0.5.dist-info/RECORD
