Metadata-Version: 2.1
Name: nonebot-adapter-spigot
Version: 0.0.5
Summary: NoneBot2与MineCraft Server互通的适配器
Home-page: https://github.com/17TheWord/nonebot-adapter-spigot
Author: 17TheWord
Author-email: 17theword@gmail.com
License: UNKNOWN
Platform: UNKNOWN
Classifier: Programming Language :: Python :: 3.9
Classifier: License :: OSI Approved :: GNU Affero General Public License v3
Classifier: Operating System :: OS Independent
License-File: LICENSE
Requires-Dist: nonebot2 (>=2.0.0rc3)
Requires-Dist: websockets (>=10.3)
